thalessecuritykey/__init__.py
thalessecuritykey/atr.py
thalessecuritykey/const.py
thalessecuritykey/device.py
thalessecuritykey/helpers.py
thalessecuritykey/hid.py
thalessecuritykey/pcsc.py
thalessecuritykey/termutils.py
thalessecuritykey-0.0.16.dist-info/licenses/LICENSE
thalessecuritykey-0.0.16.dist-info/METADATA
thalessecuritykey-0.0.16.dist-info/WHEEL
thalessecuritykey-0.0.16.dist-info/top_level.txt
thalessecuritykey-0.0.16.dist-info/RECORD
