Metadata-Version: 2.4
Name: thalessecuritykey
Version: 0.0.16
Summary: Library accessing Thales Security keys (FIDO & PKI)
License-File: LICENSE
Requires-Dist: pyscard
Requires-Dist: fido2
Requires-Dist: fido2[PCSC]
Dynamic: license-file
